.dockerignore
.env
.gitignore
Dockerfile.build
Dockerfile.run
LICENSE
MANIFEST.in
README.md
TODO.md
build.sh
dev-requirements.txt
setup.cfg
setup.py
Docker/Dockerfile
Docker/README.md
debian/.gitignore
debian/changelog
debian/compat
debian/control
debian/copyright
debian/jupyterhub.cron.d
debian/jupyterhub.default
debian/jupyterhub.dirs
debian/jupyterhub.install
debian/jupyterhub.links
debian/postinst
debian/postrm
debian/preinst
debian/prerm
debian/rules
debian/source/options
debianized_jupyterhub.egg-info/PKG-INFO
debianized_jupyterhub.egg-info/SOURCES.txt
debianized_jupyterhub.egg-info/dependency_links.txt
debianized_jupyterhub.egg-info/requires.txt
debianized_jupyterhub.egg-info/top_level.txt
docs/_static/img/README.md
docs/_static/img/devops-intelligence.graphml
docs/_static/img/devops-intelligence.png
docs/examples/System Info.ipynb
docs/examples/nginx-jhub.conf
docs/tests/extras.ipynb
etc/jupyterhub_config.py
etc/notebook.d/qgrid.json
etc/sudoers.d/jupyterhub
scripts/jupyterhub-backup
scripts/jupyterhub-launcher
systemd/jupyterhub.service