Metadata-Version: 1.1
Name: debianized-jupyterhub
Version: 1.0.0.1
Summary: Debian packaging for the jupyterhub package.
Home-page: https://github.com/1and1/debianized-jupyterhub
Author: 1&1 Group
Author-email: jh@web.de
License: BSD 3-clause
Keywords: jupyterhub,deployment,debian-packages,dh-virtualenv,devops,omnibus-packages
Platform: UNKNOWN
Classifier: Development Status :: 5 - Production/Stable
Classifier: Environment :: Web Environment
Classifier: Framework :: Jupyter
Classifier: Intended Audience :: Information Technology
Classifier: Intended Audience :: System Administrators
Classifier: Intended Audience :: Science/Research
Classifier: License :: OSI Approved :: BSD License
Classifier: Operating System :: POSIX :: Linux
Classifier: Programming Language :: Python :: 3.5
Classifier: Programming Language :: Python :: 3.6
Classifier: Programming Language :: Python :: 3.7
Classifier: Programming Language :: Python :: Implementation :: CPython
Classifier: Topic :: Scientific/Engineering :: Artificial Intelligence
Classifier: Topic :: Scientific/Engineering :: Information Analysis
Classifier: Topic :: Scientific/Engineering :: Visualization
Classifier: Topic :: Software Development :: User Interfaces
Classifier: Topic :: System :: Distributed Computing
Classifier: Topic :: Text Editors :: Integrated Development Environments (IDE)
